gwsim/__init__.py
gwsim/__main__.py
gwsim/version.py
gwsim/cli/__init__.py
gwsim/cli/batch.py
gwsim/cli/config.py
gwsim/cli/main.py
gwsim/cli/merge.py
gwsim/cli/simulate.py
gwsim/cli/simulate_utils.py
gwsim/cli/validate.py
gwsim/cli/repository/__init__.py
gwsim/cli/repository/create.py
gwsim/cli/repository/delete.py
gwsim/cli/repository/download.py
gwsim/cli/repository/list_depositions.py
gwsim/cli/repository/main.py
gwsim/cli/repository/publish.py
gwsim/cli/repository/upload.py
gwsim/cli/repository/utils.py
gwsim/cli/repository/verify.py
gwsim/cli/repository/metadata/__init__.py
gwsim/cli/repository/metadata/main.py
gwsim/cli/repository/metadata/update.py
gwsim/cli/utils/__init__.py
gwsim/cli/utils/checkpoint.py
gwsim/cli/utils/config.py
gwsim/cli/utils/config_resolution.py
gwsim/cli/utils/hash.py
gwsim/cli/utils/metadata.py
gwsim/cli/utils/retry.py
gwsim/cli/utils/simulation_plan.py
gwsim/cli/utils/template.py
gwsim/cli/utils/utils.py
gwsim/data/__init__.py
gwsim/data/serialize/__init__.py
gwsim/data/serialize/decoder.py
gwsim/data/serialize/encoder.py
gwsim/data/serialize/serializable.py
gwsim/data/time_series/__init__.py
gwsim/data/time_series/inject.py
gwsim/data/time_series/time_series.py
gwsim/data/time_series/time_series_list.py
gwsim/detector/__init__.py
gwsim/detector/base.py
gwsim/detector/utils.py
gwsim/detector/detectors/E1_2L_Aligned_Sardinia.interferometer
gwsim/detector/detectors/E1_2L_Misaligned_Sardinia.interferometer
gwsim/detector/detectors/E1_Triangle_EMR.interferometer
gwsim/detector/detectors/E1_Triangle_Sardinia.interferometer
gwsim/detector/detectors/E2_2L_Aligned_EMR.interferometer
gwsim/detector/detectors/E2_2L_Misaligned_EMR.interferometer
gwsim/detector/detectors/E2_Triangle_EMR.interferometer
gwsim/detector/detectors/E2_Triangle_Sardinia.interferometer
gwsim/detector/detectors/E3_Triangle_EMR.interferometer
gwsim/detector/detectors/E3_Triangle_Sardinia.interferometer
gwsim/detector/noise_curves/ET_10_HF_psd.txt
gwsim-0.3.2.dist-info/METADATA
gwsim-0.3.2.dist-info/WHEEL
gwsim-0.3.2.dist-info/entry_points.txt
gwsim-0.3.2.dist-info/licenses/LICENSE
gwsim-0.3.2.dist-info/RECORD
