Metadata-Version: 2.4
Name: gwsim
Version: 0.3.2
Summary: A Python package for simulating gravitational wave detector data for mock data challenges.
Project-URL: Documentation, https://leuven-gravity-institute.github.io/gwsim
Project-URL: Source, https://github.com/Leuven-Gravity-Institute/gwsim
Project-URL: Tracker, https://github.com/Leuven-Gravity-Institute/gwsim/issues
Author-email: "Isaac C. F. Wong" <chunfung.wong@kuleuven.be>
License-File: LICENSE
Classifier: Development Status :: 3 - Alpha
Classifier: Intended Audience :: Science/Research
Classifier: License :: OSI Approved :: MIT License
Classifier: Programming Language :: Python :: 3 :: Only
Classifier: Programming Language :: Python :: 3.10
Classifier: Programming Language :: Python :: 3.11
Classifier: Programming Language :: Python :: 3.12
Classifier: Topic :: Scientific/Engineering :: Astronomy
Classifier: Topic :: Scientific/Engineering :: Physics
Requires-Python: >=3.10
Requires-Dist: bilby
Requires-Dist: gengli
Requires-Dist: h5py
Requires-Dist: numpy
Requires-Dist: psutil
Requires-Dist: pycbc
Requires-Dist: pydantic
Requires-Dist: pymap3d
Requires-Dist: scipy<=1.16.3
Requires-Dist: tqdm
Requires-Dist: typer
Provides-Extra: dev
Requires-Dist: black; extra == 'dev'
Requires-Dist: flake8; extra == 'dev'
Requires-Dist: pre-commit; extra == 'dev'
Requires-Dist: pytest; extra == 'dev'
Provides-Extra: docs
Requires-Dist: mkdocs; extra == 'docs'
Requires-Dist: mkdocs-gen-files; extra == 'docs'
Requires-Dist: mkdocs-literate-nav; extra == 'docs'
Requires-Dist: mkdocs-material; extra == 'docs'
Requires-Dist: mkdocs-section-index; extra == 'docs'
Requires-Dist: mkdocstrings[python]; extra == 'docs'
Provides-Extra: test
Requires-Dist: bandit[toml]==1.8.2; extra == 'test'
Requires-Dist: black==25.12.0; extra == 'test'
Requires-Dist: check-manifest==0.50; extra == 'test'
Requires-Dist: flake8; extra == 'test'
Requires-Dist: flake8-bugbear==24.12.12; extra == 'test'
Requires-Dist: flake8-docstrings; extra == 'test'
Requires-Dist: flake8-formatter-junit-xml; extra == 'test'
Requires-Dist: flake8-pyproject; extra == 'test'
Requires-Dist: pre-commit==4.1.0; extra == 'test'
Requires-Dist: pytest-cov==6.0.0; extra == 'test'
Requires-Dist: pytest-github-actions-annotate-failures; extra == 'test'
Requires-Dist: pytest-mock<3.14.1; extra == 'test'
Requires-Dist: pytest-runner; extra == 'test'
Requires-Dist: pytest==8.3.4; extra == 'test'
Requires-Dist: shellcheck-py==0.10.0.1; extra == 'test'
